{
  "fixture_version": "fg1-fixtures-v1",
  "country_code": "US",
  "operation": "cancel",
  "scenario": "CANCEL_DEADLINE_EXPIRED",
  "document_reference": "US-cancel-DOC-001",
  "order_reference": "US-cancel-ORDER-001",
  "amount_cents": 12345,
  "currency": "LOCAL",
  "customer_tax_id": "TAX-STUB-001",
  "adapter_name": "irs_mef_stub_adapter_v1",
  "authority": "IRS",
  "canonical_status": "BUSINESS_REJECTED",
  "authority_status": "PRAZO_EXPIRADO",
  "fixture_relative_path": "fixtures/fiscal/fg1/us/cancel/cancel_deadline_expired.json"
}
